.gitignore
MANIFEST.in
README.md
setup.cfg
setup.py
qdns/__init__.py
qdns.egg-info/PKG-INFO
qdns.egg-info/SOURCES.txt
qdns.egg-info/dependency_links.txt
qdns.egg-info/top_level.txt