Metadata-Version: 1.0
Name: qdns
Version: 0.1
Summary: A threaded DNS resolver for Python
Home-page: http://github.com/basementcat/qdns
Author: Alec Elton
Author-email: alec.elton@gmail.com
License: UNKNOWN
Platform: UNKNOWN
